{
    "Ar36": {
        "error": 0.00024392176939018508, 
        "fit": "parabolic", 
        "value": 0.0075893096500638923
    }, 
    "Ar37": {
        "error": 0.013001313575075411, 
        "fit": "linear", 
        "value": 0.54390796070320557
    }, 
    "Ar38": {
        "error": 0.022618635333834427, 
        "fit": "linear", 
        "value": 1.2608675629847124
    }, 
    "Ar39": {
        "error": 0.036923353391625217, 
        "fit": "parabolic", 
        "value": 110.66802073866643
    }, 
    "Ar40": {
        "error": 0.077504493299425326, 
        "fit": "parabolic", 
        "value": 1262.4781771680637
    }, 
    "Ar41": {
        "error": 0.006218942182350729, 
        "fit": "average", 
        "value": -0.011033181121601955
    }
}