{
    "Ar36": {
        "error": 0.00027440260869936731, 
        "fit": "linear", 
        "value": 0.00968311489063629
    }, 
    "Ar37": {
        "error": 0.026533534001562858, 
        "fit": "linear", 
        "value": 0.64002192037010419
    }, 
    "Ar38": {
        "error": 0.025442448726899297, 
        "fit": "linear", 
        "value": 1.8484543181500905
    }, 
    "Ar39": {
        "error": 0.048673606145896012, 
        "fit": "linear", 
        "value": 163.65964790014502
    }, 
    "Ar40": {
        "error": 0.09695882262719395, 
        "fit": "linear", 
        "value": 1877.2200025218531
    }, 
    "Ar41": {
        "error": 0.023221606810728396, 
        "fit": "linear", 
        "value": 0.0011015449763594788
    }
}