{
    "AX": {
        "error": 0.020555187489461637, 
        "fit": "average", 
        "value": -0.010405550577626045
    }, 
    "CDD": {
        "error": 1.3204606409217909e-05, 
        "fit": "average", 
        "value": 0.00012902727661033472
    }, 
    "H1": {
        "error": 0.013555656790903925, 
        "fit": "average", 
        "value": 0.03446538319500784
    }, 
    "H2": {
        "error": 0.013725843965191723, 
        "fit": "average", 
        "value": 0.2183677544299927
    }, 
    "L1": {
        "error": 0.022272887307555635, 
        "fit": "average", 
        "value": -0.17074488990733194
    }, 
    "L2": {
        "error": 0.012974886637408277, 
        "fit": "average", 
        "value": 0.008140375413414504
    }
}