{
    "Ar36": {
        "error": 0.00065195761545610545, 
        "fit": "linear", 
        "value": 0.086134085442558489
    }, 
    "Ar37": {
        "error": 0.023069795422361945, 
        "fit": "linear", 
        "value": 0.59031056240524826
    }, 
    "Ar38": {
        "error": 0.022235806435623184, 
        "fit": "linear", 
        "value": 1.875178054480835
    }, 
    "Ar39": {
        "error": 0.04964994167853274, 
        "fit": "linear", 
        "value": 161.34378046395739
    }, 
    "Ar40": {
        "error": 0.098239715536021205, 
        "fit": "linear", 
        "value": 1885.5668272222586
    }, 
    "Ar41": {
        "error": 0.025107963097893295, 
        "fit": "linear", 
        "value": 0.25570292329476196
    }
}