{
    "Ar36": {
        "error": 0.00052028193508787404, 
        "fit": "linear", 
        "value": 0.04198086375663046
    }, 
    "Ar37": {
        "error": 0.025779156074953666, 
        "fit": "linear", 
        "value": 0.72644844714820511
    }, 
    "Ar38": {
        "error": 0.027231077091986664, 
        "fit": "linear", 
        "value": 2.2581590653399326
    }, 
    "Ar39": {
        "error": 0.045049861480124256, 
        "fit": "linear", 
        "value": 190.22091546729911
    }, 
    "Ar40": {
        "error": 0.1165150829897461, 
        "fit": "linear", 
        "value": 2194.4089747316129
    }, 
    "Ar41": {
        "error": 0.023566662118203019, 
        "fit": "linear", 
        "value": 0.0020160958787999441
    }
}