{
    "AX": {
        "error": 0.010206395060659783, 
        "fit": "average", 
        "value": -0.05309268012060784
    }, 
    "CDD": {
        "error": 3.05269750654722e-06, 
        "fit": "average", 
        "value": 7.63977295719087e-06
    }, 
    "H1": {
        "error": 0.010411932158625244, 
        "fit": "average", 
        "value": 0.0015905289008514955
    }, 
    "H2": {
        "error": 0.011412302281967554, 
        "fit": "average", 
        "value": 0.21750884433082926
    }, 
    "L1": {
        "error": 0.009914378375854706, 
        "fit": "average", 
        "value": -0.1423934302496491
    }, 
    "L2": {
        "error": 0.011281877260885972, 
        "fit": "average", 
        "value": 0.11660333452746272
    }
}