{
    "AX": {
        "error": 0.014350375140747938, 
        "fit": "average", 
        "value": -0.015491693491397503
    }, 
    "CDD": {
        "error": 1.1940007142413318e-05, 
        "fit": "average", 
        "value": 0.00012223636731505393
    }, 
    "H1": {
        "error": 0.01143637436419624, 
        "fit": "average", 
        "value": 0.025902657779321697
    }, 
    "H2": {
        "error": 0.011142188999479885, 
        "fit": "average", 
        "value": 0.19900656639389733
    }, 
    "L1": {
        "error": 0.01624502468797201, 
        "fit": "average", 
        "value": -0.18142235385554764
    }, 
    "L2": {
        "error": 0.012668936699936406, 
        "fit": "average", 
        "value": -0.023806620874772002
    }
}