{
    "AX": {
        "error": 0.00841002950549688, 
        "fit": "average", 
        "value": -0.04732587322877306
    }, 
    "CDD": {
        "error": 6.33073115989975e-06, 
        "fit": "average", 
        "value": 4.923409239078562e-05
    }, 
    "H1": {
        "error": 0.008709528132659882, 
        "fit": "average", 
        "value": -0.0032854858960490673
    }, 
    "H2": {
        "error": 0.009388061337121325, 
        "fit": "average", 
        "value": 0.2117054382487873
    }, 
    "L1": {
        "error": 0.009413533376400145, 
        "fit": "average", 
        "value": -0.17554085721502716
    }, 
    "L2": {
        "error": 0.009324324067766135, 
        "fit": "average", 
        "value": 0.12421128837417604
    }
}