{
    "AX": {
        "error": 0.009323178851749615, 
        "fit": "average", 
        "value": -0.0444406515986581
    }, 
    "CDD": {
        "error": 8.104351624850666e-06, 
        "fit": "average", 
        "value": 8.318863886718949e-05
    }, 
    "H1": {
        "error": 0.009279446701515696, 
        "fit": "average", 
        "value": 0.01484548554678137
    }, 
    "H2": {
        "error": 0.00913145866322242, 
        "fit": "average", 
        "value": -0.04740503275857514
    }, 
    "L1": {
        "error": 0.009615975792089657, 
        "fit": "average", 
        "value": -0.15620336229435958
    }, 
    "L2": {
        "error": 0.00929318177989927, 
        "fit": "average", 
        "value": 0.1305236261131035
    }
}