{
    "AX": {
        "error": 0.009286191993126549, 
        "fit": "average", 
        "value": -0.03852326656528425
    }, 
    "CDD": {
        "error": 6.518701851906384e-06, 
        "fit": "average", 
        "value": 5.2629547038426e-05
    }, 
    "H1": {
        "error": 0.00937794952889642, 
        "fit": "average", 
        "value": 0.023608334066294548
    }, 
    "H2": {
        "error": 0.010350132342712847, 
        "fit": "average", 
        "value": 0.1834180310809946
    }, 
    "L1": {
        "error": 0.010434901067272722, 
        "fit": "average", 
        "value": -0.14320895764671554
    }, 
    "L2": {
        "error": 0.009120879085399316, 
        "fit": "average", 
        "value": 0.12346996326830574
    }
}