{
    "AX": {
        "error": 0.009530873366130153, 
        "fit": "average", 
        "value": -0.047620228309339534
    }, 
    "CDD": {
        "error": 6.665262731966788e-06, 
        "fit": "average", 
        "value": 4.923409239078562e-05
    }, 
    "H1": {
        "error": 0.010705282003725497, 
        "fit": "average", 
        "value": 0.0055955443671943305
    }, 
    "H2": {
        "error": 0.008601272543196854, 
        "fit": "average", 
        "value": 0.20575821632794233
    }, 
    "L1": {
        "error": 0.009786477662988546, 
        "fit": "average", 
        "value": -0.1751746248469216
    }, 
    "L2": {
        "error": 0.009559848704232238, 
        "fit": "average", 
        "value": 0.11931690611721327
    }
}