{
    "AX": {
        "error": 0.009279553217102263, 
        "fit": "average", 
        "value": -0.046499931950691256
    }, 
    "CDD": {
        "error": 6.684260284559031e-06, 
        "fit": "average", 
        "value": 5.008295605269571e-05
    }, 
    "H1": {
        "error": 0.008982960410120937, 
        "fit": "average", 
        "value": 0.01638275963393754
    }, 
    "H2": {
        "error": 0.009531729591677258, 
        "fit": "average", 
        "value": 0.20730450712289894
    }, 
    "L1": {
        "error": 0.009973757583571701, 
        "fit": "average", 
        "value": -0.19169369450149437
    }, 
    "L2": {
        "error": 0.00919848306573973, 
        "fit": "average", 
        "value": 0.117950520751765
    }
}