{
    "AX": {
        "error": 0.008545376331322525, 
        "fit": "average", 
        "value": -0.06039560783732061
    }, 
    "CDD": {
        "error": 1.6440403230826362e-05, 
        "fit": "average", 
        "value": 9.218659212516893e-05
    }, 
    "H1": {
        "error": 0.015450231894516, 
        "fit": "average", 
        "value": -0.0156195812082539
    }, 
    "H2": {
        "error": 0.01620104456996752, 
        "fit": "average", 
        "value": -0.2897162463515997
    }, 
    "L1": {
        "error": 0.013857108732989187, 
        "fit": "average", 
        "value": -0.04265973870448458
    }, 
    "L2": {
        "error": 0.027222524446987154, 
        "fit": "average", 
        "value": -0.11864199836272746
    }
}