{
    "AX": {
        "error": 0.007643138063738802, 
        "fit": "average", 
        "value": -0.05605620555579662
    }, 
    "CDD": {
        "error": 1.4447598933311406e-05, 
        "fit": "average", 
        "value": 8.709340966864451e-05
    }, 
    "H1": {
        "error": 0.015261344100022002, 
        "fit": "average", 
        "value": -0.004378853769352039
    }, 
    "H2": {
        "error": 0.014876508197615788, 
        "fit": "average", 
        "value": -0.2726004792610183
    }, 
    "L1": {
        "error": 0.014484663536756386, 
        "fit": "average", 
        "value": -0.041814036563543294
    }, 
    "L2": {
        "error": 0.0338726943067032, 
        "fit": "average", 
        "value": -0.07416410044146081
    }
}