{
    "AX": {
        "error": 0.007568343017428035, 
        "fit": "average", 
        "value": -0.0599022454873193
    }, 
    "CDD": {
        "error": 1.7070178326417575e-05, 
        "fit": "average", 
        "value": 0.00010746613758480331
    }, 
    "H1": {
        "error": 0.011875554290589526, 
        "fit": "average", 
        "value": 0.030438071566944322
    }, 
    "H2": {
        "error": 0.014252748919640817, 
        "fit": "average", 
        "value": -0.2959058874597152
    }, 
    "L1": {
        "error": 0.013295675900169883, 
        "fit": "average", 
        "value": -0.02510173844639212
    }, 
    "L2": {
        "error": 0.03346026986797294, 
        "fit": "average", 
        "value": -0.07025424579624087
    }
}