{
    "AX": {
        "error": 0.007067670780750732, 
        "fit": "average", 
        "value": -0.067530062480364
    }, 
    "CDD": {
        "error": 1.5564636750467016e-05, 
        "fit": "average", 
        "value": 7.436045455809411e-05
    }, 
    "H1": {
        "error": 0.013220215419977623, 
        "fit": "average", 
        "value": -0.006099123977279911
    }, 
    "H2": {
        "error": 0.012886753494073425, 
        "fit": "average", 
        "value": -0.2909509235372146
    }, 
    "L1": {
        "error": 0.014840229839671149, 
        "fit": "average", 
        "value": -0.029727669939165934
    }, 
    "L2": {
        "error": 0.02496330535977324, 
        "fit": "average", 
        "value": -0.036646325956098735
    }
}