{
    "Ar36": {
        "error": 0.00050105790960216741, 
        "fit": "linear", 
        "value": 0.034311388769531229
    }, 
    "Ar37": {
        "error": 0.026133121046549385, 
        "fit": "linear", 
        "value": 1.7410586866939084
    }, 
    "Ar38": {
        "error": 0.033980244815969854, 
        "fit": "linear", 
        "value": 4.6878874665635273
    }, 
    "Ar39": {
        "error": 0.075718350633859871, 
        "fit": "linear", 
        "value": 382.24705799381132
    }, 
    "Ar40": {
        "error": 0.16740249340968363, 
        "fit": "linear", 
        "value": 4334.9494456034954
    }, 
    "Ar41": {
        "error": 0.010216552859911143, 
        "fit": "average", 
        "value": 0.30519681641521551
    }
}